is_thirteen/__init__.py
is_thirteen/is_thirteen.py
is_thirteen-0.0.2.dist-info/LICENSE.txt
is_thirteen-0.0.2.dist-info/METADATA
is_thirteen-0.0.2.dist-info/WHEEL
is_thirteen-0.0.2.dist-info/top_level.txt
is_thirteen-0.0.2.dist-info/RECORD
