Metadata-Version: 2.1
Name: is-thirteen
Version: 0.0.2
Summary: Python package to check whether an input is 13 or not
Home-page: https://github.com/amalshaji/is_thirteen
Author: Amal Shaji
Author-email: amalshaji@protonmail.com
License: MIT
Platform: UNKNOWN
Classifier: License :: OSI Approved :: MIT License
Classifier: Programming Language :: Python :: 3
Classifier: Programming Language :: Python :: 3.8
